README.md
setup.py
src/vdk/plugin/singer/adapter.py
src/vdk/plugin/singer/message_utils.py
src/vdk/plugin/singer/plugin_entry.py
src/vdk/plugin/singer/singer_command.py
src/vdk/plugin/singer/singer_data_source.py
src/vdk/plugin/singer/tap_command.py
src/vdk_singer.egg-info/PKG-INFO
src/vdk_singer.egg-info/SOURCES.txt
src/vdk_singer.egg-info/dependency_links.txt
src/vdk_singer.egg-info/entry_points.txt
src/vdk_singer.egg-info/requires.txt
src/vdk_singer.egg-info/top_level.txt
tests/test_run_ingest_singer.py
tests/test_singer_command.py